{"story":{"group_1":[{"autoTurnLast":0.2,"bg":"bg_adv_13032.jpg","bgm":"bgm05_event07","chara":[{"cheek":0,"face":"mtn_ex_020.exp.json","id":801100,"lipSynch":0,"motion":0,"pos":1}],"turnChangeIn":"fadeIn"},{"chara":[{"id":801100,"lipSynch":0}],"nameCenter":"","textCenter":"...@...","turnChangeOut":"fadeOut"},{"autoTurnLast":0.25,"chara":[{"effect":"fadeout","id":801100}],"textClear":1},{"autoTurnLast":0.1,"bg":"bg_adv_13032.jpg","bgChangeEffect":"cameraPan"},{"chara":[{"cheek":0,"face":"mtn_ex_020.exp.json","id":305101,"lipSynch":0,"motion":200,"pos":1,"soulGem":0}],"nameCenter":"Jun Kazari","textCenter":"(That's the guy from before...)","turnEffect":"thinking"},{"autoTurnLast":0.2,"bg":"bg_adv_13021.jpg","turnChangeIn":"fadeIn","turnEffect":"stop"},{"autoTurnLast":0.2,"turnEffect":"blackFrame"},{"chara":[{"cheek":0,"face":"mtn_ex_030.exp.json","id":800600,"motion":0,"pos":0},{"cheek":0,"face":"mtn_ex_030.exp.json","id":801000,"motion":0,"pos":2}],"nameLeft":"","textLeft":"...That person came back again?","turnChangeOut":"fadeOut"},{"chara":[{"id":801000}],"nameRight":"","textRight":"He's a land shark, right...@Building an apartment complex or something..."},{"chara":[{"id":800600}],"nameLeft":"","textLeft":"It seems to be a large-scale project..."},{"autoTurnLast":0.2,"bg":"bg_adv_13032.jpg","chara":[{"cheek":0,"face":"mtn_ex_020.exp.json","id":305101,"lipSynch":0,"motion":0,"pos":1,"soulGem":0}],"turnChangeIn":"fadeIn","turnEffect":"stop"},{"autoTurnLast":0.2,"turnEffect":"thinking"},{"chara":[{"id":305101,"lipSynch":0,"soulGem":0}],"nameCenter":"Jun Kazari","textCenter":"(...Land shark?  He came around the Tomorrow@Shop as well.)","turnChangeOut":"fadeOut"},{"chara":[{"eyeClose":1,"id":305101,"lipSynch":0,"soulGem":0}],"nameCenter":"Jun Kazari","textCenter":"...@...","turnEffect":"stop"},{"chara":[{"id":305101,"lipSynch":0,"motion":1,"soulGem":0}],"nameCenter":"Jun Kazari","textCenter":"(In the cellar of the Tomorrow Shop...)","turnEffect":"thinking"},{"chara":[{"id":305101,"lipSynch":0,"soulGem":0}],"nameCenter":"Jun Kazari","textCenter":"(...it's undeniable that there is a strange pot of@coins.)"},{"chara":[{"id":305101,"lipSynch":0,"soulGem":0}],"nameCenter":"Jun Kazari","textCenter":"(If it's not \"buried treasure\" or whatever...@It's got the air of a criminal element.)"},{"chara":[{"cheek":0,"eyeClose":0,"face":"mtn_ex_030.exp.json","id":305101,"motion":200,"soulGem":0}],"nameCenter":"Jun Kazari","textCenter":"I hope...@Grams will be okay.","turnEffect":"stop"},{"autoTurnLast":2.0,"bg":"bg_adv_13162.jpg","bgm":"stop","chara":[{"cheek":0,"face":"mtn_ex_030.exp.json","id":801400,"motion":0,"pos":0},{"cheek":0,"face":"mtn_ex_030.exp.json","id":800800,"motion":0,"pos":2}],"turnChangeIn":"fadeIn"},{"bgm":"bgm03_story13","chara":[{"id":800800}],"nameRight":"","textRight":"As the owner of this land, rather than selling it to@some outside developer...","turnChangeOut":"fadeOut"},{"chara":[{"id":800800}],"nameRight":"","textRight":"I could sell it to you, the owner of the Tomorrow@Shop."},{"chara":[{"id":800800}],"nameRight":"","textRight":"It would actually bring me great relief if you were@to be the one to buy it."},{"chara":[{"id":801400}],"nameLeft":"","textLeft":"...I really appreciate that, but 20 million isn't@enough, is it?"},{"chara":[{"id":801400}],"nameLeft":"","textLeft":"I'm not even sure a bank would lend to someone@old and senile like me."},{"chara":[{"id":800800}],"nameRight":"","textRight":"...This offer stays between us, of course."},{"chara":[{"id":800800}],"nameRight":"","textRight":"There have been some untoward rumors about apartment complex development in this area."},{"chara":[{"id":800800}],"nameRight":"","textRight":"Using a land shark..."},{"chara":[{"id":800800}],"nameRight":"","textRight":"I've even heard there are some bad fellows scheming something underhanded..."},{"autoTurnLast":0.25,"chara":[{"effect":"fadeout","id":801400},{"effect":"fadeout","id":800800}],"textClear":1},{"autoTurnLast":0.1,"bg":"bg_adv_13162.jpg","bgChangeEffect":"cameraPan"},{"chara":[{"cheek":0,"face":"mtn_ex_050.exp.json","id":305101,"lipSynch":0,"motion":200,"pos":1,"soulGem":0}],"nameCenter":"Jun Kazari","textCenter":"...?!"},{"chara":[{"id":305101,"lipSynch":0,"soulGem":0}],"nameCenter":"Jun Kazari","textCenter":"(Land shark...?  Apartment complex?)"},{"chara":[{"id":305101,"lipSynch":0,"soulGem":0}],"nameCenter":"Jun Kazari","textCenter":"(20 million yen...?  We're not talking chump change here!)"},{"chara":[{"cheek":0,"face":"mtn_ex_020.exp.json","id":305101,"motion":1,"pos":1,"soulGem":0}],"nameCenter":"Jun Kazari","textCenter":"Is the Tomorrow Shop being affected by this too?"},{"autoTurnLast":0.25,"chara":[{"effect":"fadeout","id":305101}],"textClear":1},{"chara":[{"cheek":0,"face":"mtn_ex_050.exp.json","id":801400,"motion":0,"pos":0},{"cheek":0,"face":"mtn_ex_030.exp.json","id":800800,"motion":0,"pos":2}],"nameLeft":"","textLeft":"Oh?@You're back, Jun."},{"chara":[{"cheek":0,"face":"mtn_ex_010.exp.json","id":800800,"motion":0,"pos":2}],"nameRight":"","textRight":"Oh, a customer?@Well, I'll be off, then..."},{"chara":[{"cheek":0,"face":"mtn_ex_050.exp.json","id":305101,"motion":0,"pos":2,"soulGem":0}],"nameRight":"Jun Kazari","textRight":"Hey, Grams.@Who was that person...?"},{"chara":[{"cheek":0,"face":"mtn_ex_050.exp.json","id":801400}],"nameLeft":"","textLeft":"Ahh, did you overhear us?"},{"chara":[{"cheek":0,"face":"mtn_ex_010.exp.json","id":801400}],"nameLeft":"","textLeft":"She's the real estate agent who manages this place."},{"chara":[{"id":305101,"motion":200,"soulGem":0}],"nameRight":"Jun Kazari","textRight":"The Tomorrow Shop's...manager?"},{"chara":[{"id":801400}],"nameLeft":"","textLeft":"I'm not the one who owns this storefront or the property."},{"chara":[{"id":801400}],"nameLeft":"","textLeft":"She's been really nice and always let me rent here pretty cheaply."},{"chara":[{"cheek":0,"face":"mtn_ex_030.exp.json","id":305101,"motion":300,"soulGem":0}],"nameRight":"Jun Kazari","textRight":"Ah, I see..."},{"chara":[{"cheek":0,"face":"mtn_ex_030.exp.json","id":801400}],"nameLeft":"","textLeft":"I suppose it's time for the Tomorrow Shop to close@up shop..."},{"chara":[{"cheek":0,"face":"mtn_ex_050.exp.json","id":305101,"motion":400,"soulGem":0}],"nameRight":"Jun Kazari","textRight":"[chara:305101:effect_emotion_surprise_0][se:7226_shock]Ehh...?!"},{"chara":[{"id":305101,"motion":0,"soulGem":0}],"nameRight":"Jun Kazari","textRight":"Wh...what?!"},{"chara":[{"id":801400}],"nameLeft":"","textLeft":"The landlady is in a bit of a situation and needs@some funds to get out of it."},{"chara":[{"id":801400}],"nameLeft":"","textLeft":"She plans on selling all of her plots and it seems@she's looking around for a buyer."},{"chara":[{"cheek":0,"face":"mtn_ex_010.exp.json","id":801400}],"nameLeft":"","textLeft":"She's such an understanding landlady..."},{"chara":[{"id":801400}],"nameLeft":"","textLeft":"She's saying she would sell it to me for a good@price..."},{"chara":[{"cheek":0,"face":"mtn_ex_030.exp.json","id":801400}],"nameLeft":"","textLeft":"But even so, the 20 million yen I have isn't enough."},{"chara":[{"id":801400}],"nameLeft":"","textLeft":"I started this shop together with my husband...@But it just might be time to retire..."},{"chara":[{"cheek":0,"eyeClose":1,"face":"mtn_ex_030.exp.json","id":305101,"motion":200,"soulGem":0}],"nameRight":"Jun Kazari","textRight":"No way..."},{"chara":[{"id":801400}],"nameLeft":"","textLeft":"I'm too old to take out a loan, so...@That's that, then..."},{"chara":[{"id":801400}],"nameLeft":"","textLeft":"An apartment complex, huh..."},{"chara":[{"id":801400}],"nameLeft":"","textLeft":"Land around here is in demand, I hear..."},{"chara":[{"id":801400}],"nameLeft":"","textLeft":"Looks like the Tomorrow Shop will just be@swallowed up in all of that."},{"autoTurnLast":0.25,"chara":[{"effect":"fadeout","id":801400},{"effect":"fadeout","id":305101}],"textClear":1},{"chara":[{"cheek":0,"face":"mtn_ex_050.exp.json","id":305101,"lipSynch":0,"motion":0,"pos":1,"soulGem":0}],"nameCenter":"Jun Kazari","textCenter":"(Wait...!)","turnEffect":"thinking"},{"chara":[{"id":305101,"lipSynch":0,"soulGem":0}],"nameCenter":"Jun Kazari","textCenter":"(Is this what that land shark is after?)"},{"chara":[{"cheek":0,"eyeClose":1,"face":"mtn_ex_030.exp.json","id":305101,"lipSynch":0,"motion":1,"soulGem":0}],"nameCenter":"Jun Kazari","textCenter":"(The landlady's \"situation\" is suspicious in the first place...)"},{"chara":[{"id":305101,"lipSynch":0,"soulGem":0}],"nameCenter":"Jun Kazari","textCenter":"(Then there are those super suspicious gold coins@in the floor of the Tomorrow Shop...)"},{"chara":[{"id":305101,"lipSynch":0,"soulGem":0}],"nameCenter":"Jun Kazari","textCenter":"(I wonder if there could be even more of them if the floor was pulled open wider?)"},{"chara":[{"id":305101,"lipSynch":0,"soulGem":0}],"nameCenter":"Jun Kazari","textCenter":"(Maybe it's in order to get ahold of those coins...)"},{"chara":[{"id":305101,"lipSynch":0,"soulGem":0}],"nameCenter":"Jun Kazari","textCenter":"(...that the bad guy wants this land?)"},{"chara":[{"cheek":0,"eyeClose":0,"face":"mtn_ex_050.exp.json","id":305101,"lipSynch":0,"motion":200,"soulGem":0}],"nameCenter":"Jun Kazari","textCenter":"(I've got to tell Grams about--@No, wait...)"},{"chara":[{"id":305101,"lipSynch":0,"soulGem":0}],"nameCenter":"Jun Kazari","textCenter":"(Just by telling her about it...@I could be putting her in danger, too...?)"},{"chara":[{"cheek":0,"eyeClose":1,"face":"mtn_ex_020.exp.json","id":305101,"lipSynch":0,"motion":0,"soulGem":0}],"nameCenter":"Jun Kazari","textCenter":"...","turnEffect":"stop"},{"autoTurnLast":0.25,"chara":[{"id":305101,"pos":2}],"textClear":1},{"chara":[{"cheek":0,"face":"mtn_ex_050.exp.json","id":801400,"motion":0,"pos":0}],"nameLeft":"","textLeft":"What's going on, dear?@You're sweating."},{"chara":[{"cheek":0,"face":"mtn_ex_030.exp.json","id":305101,"motion":300,"soulGem":0}],"nameRight":"Jun Kazari","textRight":"...Ah-- No, it's nothing."},{"chara":[{"cheek":0,"face":"mtn_ex_030.exp.json","id":801400}],"nameLeft":"","textLeft":"I'm sorry.  This talk about shutting down the shop@really was a shock to you, wasn't it?"},{"chara":[{"id":801400}],"nameLeft":"","textLeft":"You come to the shop just about every single day."},{"chara":[{"id":801400}],"nameLeft":"","textLeft":"I thought it would be best..."},{"chara":[{"id":801400}],"nameLeft":"","textLeft":"...to go ahead and tell you as soon as possible..."},{"chara":[{"cheek":0,"face":"mtn_ex_011.exp.json","id":305101,"motion":0,"soulGem":0}],"nameRight":"Jun Kazari","textRight":"Oh... Thank you."},{"chara":[{"cheek":0,"face":"mtn_ex_010.exp.json","id":305101,"motion":200,"soulGem":0}],"nameRight":"Jun Kazari","textRight":"...I'd better get heading home."},{"chara":[{"cheek":0,"face":"mtn_ex_010.exp.json","id":801400,"motion":0}],"nameLeft":"","textLeft":"Okay then, bye.@See you tomorrow."},{"chara":[{"cheek":0,"eyeClose":1,"face":"mtn_ex_030.exp.json","id":305101,"lipSynch":0,"soulGem":0}],"nameRight":"Jun Kazari","textRight":"..."},{"autoTurnFirst":3.0,"bg":"bg_adv_narration.jpg","bgm":"stop","chara":[{"cheek":0,"eyeClose":0,"face":"mtn_ex_020.exp.json","id":305101,"motion":1,"pos":1,"soulGem":0,"voice":"vo_char_3051_00_04"}],"nameCenter":"Jun Kazari","textCenter":"That guy...@Could be a really bad character...","turnChangeIn":"fadeIn","turnChangeOut":"fadeOut"},{"autoTurnFirst":3.0,"chara":[{"eyeClose":1,"id":305101,"motion":200}]},{"chara":[{"id":305101}]},{"autoTurnLast":2.0,"turnChangeIn":"fadeIn"}]},"version":3}