{"story":{"group_1":[{"autoTurnLast":0.01,"bg":"bg_adv_13141.jpg","bgm":"bgm01_anime03","chara":[{"cheek":2,"face":"mtn_ex_050.exp.json","id":102501,"motion":0,"pos":1}],"turnChangeIn":"fadeIn"},{"chara":[{"id":102501,"motion":200}],"nameCenter":"Shizuka","textCenter":"H-hey...do people really go swimming@in those outfits?","turnChangeOut":"fadeOut"},{"chara":[{"cheek":2,"face":"mtn_ex_030.exp.json","id":102501}],"nameCenter":"Shizuka","textCenter":"Surely this \"telly-vision\" show@is exaggerating, yes...?"},{"autoTurnLast":0.2,"chara":[{"id":102501,"pos":0}],"textClear":1},{"chara":[{"cheek":0,"face":"mtn_ex_010.exp.json","id":102601,"motion":200,"pos":2}],"nameRight":"Chiharu","textRight":"No, it's true.@That's what swimsuits are for."},{"chara":[{"cheek":0,"face":"mtn_ex_050.exp.json","id":102701,"motion":1,"pos":2}],"nameRight":"Sunao","textRight":"Have you never worn one before,@Shizuka?"},{"chara":[{"id":102501,"motion":300}],"nameLeft":"Shizuka","textLeft":"A-absolutely not... There's no way@I could dress like that..."},{"chara":[{"eyeClose":1,"id":102501}],"nameLeft":"Shizuka","textLeft":"It's...hardly more than underwear..."},{"chara":[{"cheek":0,"face":"mtn_ex_050.exp.json","id":102601,"motion":1,"pos":2}],"nameRight":"Chiharu","textRight":"Huh? But you go swimming, don't you?"},{"chara":[{"id":102601}],"nameRight":"Chiharu","textRight":"What have you been swimming in, then?@[chara:102601:lipSynch_0][wait:0.8][chara:102601:motion_400][chara:102601:lipSynch_1]Wait - you can't mean..."},{"chara":[{"cheek":0,"eyeClose":0,"face":"mtn_ex_050.exp.json","id":102501,"motion":0}],"nameLeft":"Shizuka","textLeft":"Um... Well, it's hard to describe..."},{"chara":[{"cheek":0,"face":"mtn_ex_010.exp.json","id":102501,"motion":100},{"id":102601,"motion":0}],"nameLeft":"Shizuka","textLeft":"I know! Think back to show we just@watched about the female divers."},{"chara":[{"id":102501}],"nameLeft":"Shizuka","textLeft":"I'd say my garment looks similar to@what they wore."},{"chara":[{"cheek":0,"face":"mtn_ex_010.exp.json","id":102701,"motion":100,"pos":2}],"nameRight":"Sunao","textRight":"I see... So it's something less revealing@than a typical swimsuit."},{"chara":[{"cheek":0,"face":"mtn_ex_010.exp.json","id":102601,"motion":0,"pos":2}],"nameRight":"Chiharu","textRight":"Why not take this as an opportunity to@buy a swimsuit of your own, Shizuka?"},{"chara":[{"cheek":1,"face":"mtn_ex_050.exp.json","id":102501,"motion":400}],"nameLeft":"Shizuka","textLeft":"...Huh?"},{"chara":[{"cheek":0,"face":"mtn_ex_011.exp.json","id":102601,"motion":100}],"nameRight":"Chiharu","textRight":"If you have a swimsuit, that means you@can visit the beach and the pool!"},{"chara":[{"cheek":2,"face":"mtn_ex_030.exp.json","id":102501,"motion":200}],"nameLeft":"Shizuka","textLeft":"Me, wearing a swimsuit...? In public...?@With so much exposure...?"},{"chara":[{"cheek":0,"face":"mtn_ex_010.exp.json","id":102601,"motion":1}],"nameRight":"Chiharu","textRight":"It's completely normal."},{"chara":[{"id":102601}],"nameRight":"Chiharu","textRight":"I have one, and so does Sunao, right?"},{"chara":[{"cheek":0,"face":"mtn_ex_011.exp.json","id":102701,"motion":100,"pos":2}],"nameRight":"Sunao","textRight":"Of course."},{"chara":[{"cheek":2,"face":"mtn_ex_050.exp.json","id":102501,"lipSynch":0,"motion":0}],"nameLeft":"Shizuka","textLeft":"..."},{"chara":[{"cheek":2,"face":"mtn_ex_030.exp.json","id":102501}],"nameLeft":"Shizuka","textLeft":"Then...I suppose I can take a look..."},{"chara":[{"cheek":0,"face":"mtn_ex_011.exp.json","id":102601,"motion":100,"pos":2}],"nameRight":"Chiharu","textRight":"Hooray!"},{"chara":[{"cheek":0,"face":"mtn_ex_010.exp.json","id":102701,"motion":200,"pos":2}],"nameRight":"Sunao","textRight":"Let us be on our way."},{"autoTurnLast":2,"bg":"bg_adv_21411.jpg","chara":[{"cheek":2,"face":"mtn_ex_030.exp.json","id":102551,"motion":1,"pos":1}],"turnChangeIn":"fadeIn"},{"chara":[{"id":102551,"lipSynch":0}],"nameCenter":"Shizuka","textCenter":"...","turnChangeOut":"fadeOut"},{"chara":[{"eyeClose":1,"id":102551}],"nameCenter":"Shizuka","textCenter":"Well...how is it?"},{"autoTurnLast":0.2,"chara":[{"effect":"fadeout","id":102551}],"textClear":1},{"chara":[{"cheek":0,"face":"mtn_ex_011.exp.json","id":102701,"motion":100,"pos":2},{"cheek":0,"face":"mtn_ex_010.exp.json","id":102601,"motion":0,"pos":0}],"nameRight":"Sunao","textRight":"It looks very nice."},{"chara":[{"cheek":0,"face":"mtn_ex_011.exp.json","id":102601,"motion":200}],"nameLeft":"Chiharu","textLeft":"Yeah! It's so cute!"},{"chara":[{"cheek":0,"face":"mtn_ex_010.exp.json","id":800600,"motion":0,"pos":2}],"nameRight":"","textRight":"Yes, it looks great on you.@It suits your figure perfectly."},{"autoTurnLast":0.2,"chara":[{"effect":"fadeout","id":102601},{"effect":"fadeout","id":800600}],"textClear":1},{"chara":[{"cheek":2,"face":"mtn_ex_050.exp.json","id":102551,"motion":300,"pos":1}],"nameCenter":"Shizuka","textCenter":"I-it does...?"},{"chara":[{"id":102551}],"nameCenter":"Shizuka","textCenter":"If everyone says as much,@then perhaps I'll get it..."},{"chara":[{"cheek":2,"face":"mtn_ex_030.exp.json","id":102551,"motion":200}],"nameCenter":"Shizuka","textCenter":"But still, walking about in public@like this...it's...um..."},{"autoTurnLast":0.2,"chara":[{"effect":"fadeout","id":102551}],"textClear":1},{"chara":[{"cheek":0,"face":"mtn_ex_010.exp.json","id":102701,"motion":1,"pos":2},{"cheek":0,"face":"mtn_ex_010.exp.json","id":102601,"motion":0,"pos":0}],"nameRight":"Sunao","textRight":"Why don't you show it to the others@in the clan as well?"},{"chara":[{"cheek":0,"face":"mtn_ex_011.exp.json","id":102701}],"nameRight":"Sunao","textRight":"I'm sure they'll have nothing but praise."},{"chara":[{"id":102601,"motion":200}],"nameLeft":"Chiharu","textLeft":"Then it won't feel so embarrassing,@right?"},{"autoTurnLast":0.2,"chara":[{"effect":"fadeout","id":102601},{"effect":"fadeout","id":102701}],"textClear":1},{"chara":[{"cheek":1,"face":"mtn_ex_050.exp.json","id":102551,"motion":0,"pos":1}],"nameCenter":"Shizuka","textCenter":"...Do neither of you feel that way@when wearing swimsuits?"},{"autoTurnLast":0.2,"chara":[{"effect":"fadeout","id":102551}],"textClear":1},{"chara":[{"cheek":1,"face":"mtn_ex_050.exp.json","id":102601,"motion":0,"pos":0},{"cheek":1,"face":"mtn_ex_050.exp.json","id":102701,"motion":0,"pos":2}],"nameCenter":"Chiharu & Sunao","textCenter":"..."},{"chara":[{"cheek":1,"face":"mtn_ex_030.exp.json","id":102701,"motion":300}],"nameRight":"Sunao","textRight":"Well, it's not that I don't ever feel@self-conscious, but..."},{"chara":[{"cheek":0,"face":"mtn_ex_011.exp.json","id":102601,"motion":100}],"nameLeft":"Chiharu","textLeft":"Everyone dresses like this at the beach@or pool, so you won't stick out!"},{"autoTurnLast":0.2,"chara":[{"effect":"fadeout","id":102601},{"effect":"fadeout","id":102701}],"textClear":1},{"chara":[{"cheek":1,"face":"mtn_ex_050.exp.json","id":102551,"motion":200,"pos":1}],"nameCenter":"Shizuka","textCenter":"...I see."},{"chara":[{"id":102551}],"nameCenter":"Shizuka","textCenter":"If you two are so certain,@then I'll buy this..."},{"chara":[{"cheek":1,"face":"mtn_ex_010.exp.json","id":102551,"motion":100}],"nameCenter":"Shizuka","textCenter":"...because I'd like to visit the beach@and the \"puhl\" as well."},{"autoTurnLast":0.2,"chara":[{"effect":"fadeout","id":102551}],"textClear":1},{"chara":[{"cheek":0,"face":"mtn_ex_011.exp.json","id":102601,"motion":200,"pos":0},{"cheek":0,"face":"mtn_ex_010.exp.json","id":102701,"motion":1,"pos":2}],"nameLeft":"Chiharu","textLeft":"Yeah, yeah! I think it's a great idea!"},{"chara":[{"cheek":0,"face":"mtn_ex_011.exp.json","id":102701,"motion":100}],"nameRight":"Sunao","textRight":"Indeed...!"},{"autoTurnLast":2,"bg":"bg_adv_13141.jpg","bgm":"stop","chara":[{"cheek":2,"face":"mtn_ex_030.exp.json","id":102551,"motion":0,"pos":0},{"cheek":0,"face":"mtn_ex_010.exp.json","id":102650,"motion":0,"pos":1},{"cheek":0,"face":"mtn_ex_010.exp.json","id":102750,"motion":1,"pos":2}],"turnChangeIn":"fadeIn"},{"bgm":"bgm23_tokime02","chara":[{"id":102551,"motion":100}],"nameLeft":"Shizuka","textLeft":"...What do you all think?","turnChangeOut":"fadeOut"},{"autoTurnLast":0.2,"chara":[{"effect":"fadeout","id":102650},{"effect":"fadeout","id":102750}],"textClear":1},{"chara":[{"cheek":0,"face":"mtn_ex_030.exp.json","id":305801,"motion":1,"pos":2}],"nameRight":"Ryouko","textRight":"First off, why are you@wearing a swimsuit here?"},{"chara":[{"cheek":0,"face":"mtn_ex_010.exp.json","id":102650,"motion":1,"pos":0}],"nameLeft":"Chiharu","textLeft":"Well, Shizuka's never worn@a swimsuit before,"},{"chara":[{"id":102650}],"nameLeft":"Chiharu","textLeft":"so we helped her buy one."},{"chara":[{"cheek":0,"face":"mtn_ex_011.exp.json","id":102650,"motion":200,"pos":0}],"nameLeft":"Chiharu","textLeft":"It's her very first swimsuit!"},{"chara":[{"cheek":0,"face":"mtn_ex_010.exp.json","id":102750,"motion":1,"pos":2}],"nameRight":"Sunao","textRight":"She was embarrassed to wear one@in public, however."},{"chara":[{"id":102750}],"nameRight":"Sunao","textRight":"We wanted to help her get used to being@seen by people beforehand."},{"chara":[{"cheek":2,"face":"mtn_ex_030.exp.json","id":102551,"motion":300,"pos":0}],"nameLeft":"Shizuka","textLeft":"Um...does it look strange?"},{"chara":[{"cheek":0,"face":"mtn_ex_010.exp.json","id":305801,"motion":0,"pos":2}],"nameRight":"Ryouko","textRight":"No, it's not strange in and of itself."},{"chara":[{"cheek":0,"face":"mtn_ex_030.exp.json","id":305801,"motion":100}],"nameRight":"Ryouko","textRight":"It's just...I can't think of anything more@inappropriate to wear inside a temple."},{"chara":[{"cheek":0,"face":"mtn_ex_011.exp.json","id":305801}],"nameRight":"Ryouko","textRight":"Still, taking the swimsuit on its own,@I think it looks pretty good, yeah?"},{"chara":[{"cheek":1,"face":"mtn_ex_010.exp.json","id":102551,"motion":0,"pos":0}],"nameLeft":"Shizuka","textLeft":"So it's not strange, then...@Thank goodness."},{"chara":[{"cheek":0,"face":"mtn_ex_011.exp.json","id":304701,"motion":100,"pos":2}],"nameRight":"Chika","textRight":"The three of you picked it out together?@It's very cute."},{"chara":[{"id":102551,"motion":1}],"nameLeft":"Shizuka","textLeft":"Th...thank you..."},{"chara":[{"cheek":0,"face":"mtn_ex_010.exp.json","id":103401,"motion":1,"pos":2}],"nameRight":"Asahi","textRight":"It truly becomes you."},{"chara":[{"id":103401}],"nameRight":"Asahi","textRight":"It would be a shame if you didn't go out@and use it to its fullest."},{"chara":[{"cheek":0,"face":"mtn_ex_011.exp.json","id":103401,"motion":100}],"nameRight":"Asahi","textRight":"Have confidence in yourself!"},{"chara":[{"cheek":1,"face":"mtn_ex_011.exp.json","id":102551,"motion":200}],"nameLeft":"Shizuka","textLeft":"Well...since we went through such lengths@to choose this, then I'll do just that."},{"autoTurnLast":0.2,"chara":[{"effect":"fadeout","id":103401},{"effect":"fadeout","id":102551}],"textClear":1},{"chara":[{"cheek":0,"face":"mtn_ex_030.exp.json","id":305801,"motion":1,"pos":2},{"cheek":0,"face":"mtn_ex_010.exp.json","id":102750,"motion":0,"pos":0}],"nameRight":"Ryouko","textRight":"So that explains Shizuka...now what are you@two doing in your swimsuits?"},{"chara":[{"cheek":0,"face":"mtn_ex_030.exp.json","id":102750,"motion":200,"pos":0}],"nameLeft":"Sunao","textLeft":"Shizuka was too nervous to wear hers alone,@you see..."},{"chara":[{"cheek":0,"face":"mtn_ex_020.exp.json","id":102650,"motion":0,"pos":0}],"nameLeft":"Chiharu","textLeft":"And besides..."},{"chara":[{"cheek":0,"face":"mtn_ex_011.exp.json","id":102650,"motion":100,"pos":0}],"nameLeft":"Chiharu","textLeft":"I bought a new one, too, so I want to@show it off to everyone!"},{"autoTurnLast":0.5,"chara":[{"effect":"fadeout","id":305801},{"effect":"fadeout","id":102650}],"textClear":1},{"autoTurnLast":1,"chara":[{"cheek":1,"face":"mtn_ex_010.exp.json","id":102551,"motion":100,"pos":1}],"textClear":1},{"nameRight":"Chika's Voice","textRight":"Alright, I'll take a picture."},{"nameNarration":"","narration":"*Ker-chak*[flashEffect:flashWhite1][surround:7023_camera]","narrationBg":"","narrationEffect":"in"},{"chara":[{"cheek":1,"face":"mtn_ex_011.exp.json","id":102551,"motion":0}],"nameCenter":"Shizuka","narrationEffect":"out","textCenter":"Thank you."},{"chara":[{"cheek":0,"face":"mtn_ex_010.exp.json","id":102551,"motion":1}],"nameCenter":"Shizuka","textCenter":"Do you think my mother would be surprised@if I sent her that photo of me in my swimsuit? "},{"autoTurnLast":0.2,"chara":[{"id":102551,"pos":0}],"textClear":1},{"chara":[{"cheek":0,"face":"mtn_ex_010.exp.json","id":304701,"motion":1,"pos":2}],"nameRight":"Chika","textRight":"I doubt she's ever seen one in the village,@so she probably will."},{"autoTurnLast":0.2,"chara":[{"effect":"fadeout","id":102551},{"effect":"fadeout","id":304701}],"textClear":1},{"chara":[{"cheek":0,"face":"mtn_ex_010.exp.json","id":102650,"motion":200,"pos":0},{"cheek":0,"face":"mtn_ex_010.exp.json","id":102750,"motion":1,"pos":2}],"nameLeft":"Chiharu","textLeft":"It looks like you've gotten used@to wearing it now, Shizuka."},{"chara":[{"cheek":0,"face":"mtn_ex_011.exp.json","id":102750}],"nameRight":"Sunao","textRight":"*Giggle* Now we can make memories@at the beach, too."},{"chara":[{"effect":"fadeout","id":102750},{"effect":"fadeout","id":102650},{"cheek":0,"face":"mtn_ex_050.exp.json","id":102551,"motion":0,"pos":1}],"nameNarration":"","narration":"*Jingle♪*[se:7106_telmail]","narrationBg":"bg_adv_13141.jpg","narrationEffect":"in"},{"chara":[{"id":102551}],"nameCenter":"Shizuka","narrationEffect":"out","textCenter":"Oh, Mother responded..."},{"chara":[{"cheek":0,"face":"mtn_ex_001.exp.json","id":102551,"lipSynch":0,"motion":200}],"nameCenter":"Shizuka","textCenter":"..."},{"chara":[{"cheek":1,"face":"mtn_ex_011.exp.json","id":102551}],"nameCenter":"Shizuka","textCenter":"*Giggle* She said it's cute!"},{"chara":[{"cheek":0,"face":"mtn_ex_050.exp.json","id":102551,"motion":0}],"nameNarration":"","narration":"*Jingle♪*[se:7106_telmail]","narrationBg":"bg_adv_13141.jpg","narrationEffect":"in"},{"chara":[{"id":102551}],"nameCenter":"Shizuka","narrationEffect":"out","textCenter":"Oh, Mother again..."},{"chara":[{"cheek":1,"face":"mtn_ex_030.exp.json","id":102551,"motion":300}],"nameCenter":"Shizuka","textCenter":"...But she also said I mustn't wear it@in the temple."},{"autoTurnLast":0.2,"chara":[{"effect":"fadeout","id":102551}],"textClear":1},{"chara":[{"cheek":0,"face":"mtn_ex_030.exp.json","id":305801,"motion":100,"pos":2},{"cheek":0,"face":"mtn_ex_030.exp.json","id":102650,"motion":0,"pos":0}],"nameRight":"Ryouko","textRight":"Right..."},{"chara":[{"cheek":0,"face":"mtn_ex_010.exp.json","id":102650,"motion":200}],"nameLeft":"Chiharu","textLeft":"We'll take a picture from the beach@or the pool next time!"},{"autoTurnLast":2,"turnChangeIn":"fadeIn"}]},"version":3}
