{"story":{"group_1":[{"autoTurnLast":0.01,"turnChangeIn":"fadeIn"},{"bgm":"bgm03_story19","nameNarration":"Natsuki","narration":"It's finally time for the student council@sponsored Dark-Colored Halloween Party!","narrationBg":"bg_adv_21902.jpg","narrationEffect":"in","turnChangeOut":"fadeOut"},{"narration":"Among the attractions@was the ever so slight horror experience@run by students dressed as \"nobodies\"—@the \"Everlasting Darkness Tour\"..."},{"autoTurnLast":0.5,"bg":"bg_adv_21902.jpg","chara":[{"cheek":0,"face":"mtn_ex_010.exp3.json","id":300251,"motion":0,"pos":2},{"cheek":0,"face":"mtn_ex_010.exp3.json","id":800303,"motion":0,"pos":0}],"narrationEffect":"out","turnChangeIn":"fadeIn"},{"chara":[{"id":300251}],"nameRight":"Natsuki","textRight":"You good if I set the box of candy here?","turnChangeOut":"fadeOut"},{"chara":[{"id":800303}],"nameLeft":"","textLeft":"Yeah, you're a big help carrying it.@Sorry to keep you so busy."},{"chara":[{"cheek":0,"face":"mtn_ex_011.exp3.json","id":300251,"motion":100}],"nameRight":"Natsuki","textRight":"The feeling's mutual, so don't worry about it!"},{"autoTurnLast":0.5,"chara":[{"effect":"fadeout","id":800303}],"textClear":1},{"autoTurnLast":0.2,"chara":[{"id":300251,"pos":1}],"textClear":1},{"chara":[{"cheek":0,"face":"mtn_ex_010.exp3.json","id":300251,"motion":1}],"nameCenter":"Natsuki","textCenter":"Alright, it's about time for me too. I need to@get back to being the \"nameless dancer\"."},{"autoTurnLast":0.2,"chara":[{"id":300251,"pos":0}],"textClear":1},{"chara":[{"cheek":0,"face":"mtn_ex_010.exp3.json","id":300801,"motion":1,"pos":2}],"nameRight":"Akira","textRight":"I see you're working."},{"chara":[{"id":300251,"motion":100}],"nameLeft":"Natsuki","textLeft":"Akira! You showed up!"},{"chara":[{"id":300801,"motion":200}],"nameRight":"Akira","textRight":"I heard rumors of the event so I thought@I'd come take a peek."},{"chara":[{"cheek":0,"face":"mtn_ex_050.exp3.json","id":300801}],"nameRight":"Akira","textRight":"And now that I'm here...that's an amazing outfit."},{"chara":[{"cheek":0,"face":"mtn_ex_030.exp3.json","id":300251}],"nameLeft":"Natsuki","textLeft":"I told them I wanted something easy to move in,@but it ended up more like a swimsuit..."},{"chara":[{"cheek":0,"face":"mtn_ex_030.exp3.json","id":300801,"motion":0}],"nameRight":"Akira","textRight":"No one in the area's wearing anything like yours,@so it stands out way more."},{"chara":[{"eyeClose":1,"id":300251,"motion":301}],"nameLeft":"Natsuki","textLeft":"[chara:300251:effect_emotion_sad_0][se:7224_fall_into]Ugh...it does."},{"chara":[{"cheek":0,"face":"mtn_ex_050.exp3.json","id":300801,"motion":1}],"nameRight":"Akira","textRight":"But like, why did you dress so loosely?"},{"chara":[{"cheek":0,"eyeClose":0,"face":"mtn_ex_010.exp3.json","id":300251,"motion":1}],"nameLeft":"Natsuki","textLeft":"I guess I just wanted to jump in and start helping@people as soon as I could."},{"chara":[{"cheek":0,"face":"mtn_ex_010.exp3.json","id":300801}],"nameRight":"Akira","textRight":"Heeh, that sounds like my Natsuki."},{"chara":[{"id":300251}],"nameLeft":"Natsuki","textLeft":"Oh, and..."},{"bgm":"stop","chara":[{"cheek":0,"face":"mtn_ex_050.exp3.json","id":300251},{"cheek":0,"face":"mtn_ex_050.exp3.json","id":300801}],"nameCenter":"Kanagi's Voice","textBg":"shout","textCenter":"Utsuho!@Quick, get over here!!"},{"chara":[{"id":300251,"motion":400}],"nameLeft":"Natsuki","textLeft":"[chara:300251:effect_emotion_surprise_0][se:7226_shock]Ah...!@Sorry, give me a second."},{"autoTurnLast":0.5,"chara":[{"effect":"fadeout","id":300251}],"textClear":1},{"chara":[{"id":300801,"motion":400}],"nameRight":"Akira","textRight":"Natsuki?!"},{"autoTurnLast":0.5,"bg":"bg_adv_21892.jpg","chara":[{"cheek":0,"face":"mtn_ex_030.exp3.json","id":801300,"motion":0,"pos":2},{"cheek":0,"face":"mtn_ex_030.exp3.json","id":121600,"motion":0,"pos":0}],"turnChangeIn":"rollInFast"},{"bgm":"bgm03_story16","chara":[{"id":801300}],"nameRight":"","textBg":"shout","textRight":"[chara:801300:effect_emotion_sad_0][se:7224_fall_into]I'm scared of ghooosts!!@Waaaahh!!","turnChangeOut":"rollOutFast"},{"chara":[{"id":121600,"motion":300}],"nameLeft":"Kanagi","textLeft":"Mmngh...how awkward...@I tried to keep my acting mild, and yet..."},{"chara":[{"cheek":0,"face":"mtn_ex_050.exp3.json","id":300251,"motion":300,"pos":2}],"nameRight":"Natsuki","textRight":"Let me guess, it happened again?"},{"chara":[{"id":121600,"motion":200}],"nameLeft":"Kanagi","textLeft":"It pains me to ask even though you are acting@as well, Utsuho... Apologies, but could I also leave@this one to you?"},{"chara":[{"cheek":0,"face":"mtn_ex_011.exp3.json","id":300251,"motion":100}],"nameRight":"Natsuki","textRight":"Please let me take care of it!"},{"autoTurnLast":0.5,"bg":"bg_adv_21902.jpg","chara":[{"cheek":0,"face":"mtn_ex_030.exp3.json","id":801300,"motion":0,"pos":2},{"cheek":0,"face":"mtn_ex_010.exp3.json","id":300251,"motion":0,"pos":0}],"turnChangeIn":"rollInFast"},{"chara":[{"id":801300}],"nameRight":"","textRight":"Uuu...ghosts are scary~...","turnChangeOut":"rollOutFast"},{"chara":[{"id":300251,"motion":200}],"nameLeft":"Natsuki","textLeft":"Look, she left the area and vanished!"},{"chara":[{"id":801300}],"nameRight":"","textRight":"*Sniffle...* *Sniffle...*@[chara:801300:lipSynch_0][wait:0.8][chara:801300:lipSynch_1][chara:801300:effect_shake]Waaaahh!!"},{"chara":[{"cheek":0,"face":"mtn_ex_030.exp3.json","id":300251,"lipSynch":0,"motion":300}],"nameLeft":"Natsuki","textLeft":"(Well I'll be darned~...@He's really got it bad.)"},{"chara":[{"cheek":0,"face":"mtn_ex_020.exp3.json","id":300251,"lipSynch":0}],"nameLeft":"Natsuki","textLeft":"(Then it's come to this...!)"},{"chara":[{"cheek":0,"face":"mtn_ex_010.exp3.json","id":300251,"motion":1}],"nameLeft":"Natsuki","textLeft":"In that case, I'll put a good luck charm on you."},{"chara":[{"id":801300}],"nameRight":"","textRight":"*Sniffle...*@Good luck charm...?"},{"chara":[{"id":300251}],"nameLeft":"Natsuki","textLeft":"It's just the thing to give you the courage@to face the ghost!"},{"chara":[{"cheek":0,"face":"mtn_ex_011.exp3.json","id":300251,"motion":100,"pos":0}],"nameLeft":"Natsuki","textLeft":"YOU CAN DO IT!@GO FIGHT WIN!!"},{"autoTurnLast":0.5,"flashEffect":"flashWhite2","textClear":1},{"bgm":"stop","chara":[{"cheek":0,"face":"mtn_ex_050.exp3.json","id":801300,"lipSynch":0}],"nameRight":"","textRight":"...!!"},{"chara":[{"cheek":0,"face":"mtn_ex_010.exp3.json","id":300251,"motion":0}],"nameLeft":"Natsuki","textLeft":"Well? Feeling braver?"},{"bgm":"bgm01_anime02","chara":[{"id":801300}],"nameRight":"","textRight":"It's real...@All my fear is gone."},{"chara":[{"cheek":0,"face":"mtn_ex_011.exp3.json","id":801300}],"nameRight":"","textRight":"Maybe now I can try it one more time!"},{"chara":[{"cheek":0,"face":"mtn_ex_011.exp3.json","id":300251,"motion":200}],"nameLeft":"Natsuki","textLeft":"Sure thing!@Sounds like you're okay!"},{"chara":[{"cheek":0,"face":"mtn_ex_010.exp3.json","id":300251}],"nameLeft":"Natsuki","textLeft":"And if you ever feel scared again, just remember@this good luck charm:"},{"chara":[{"cheek":0,"face":"mtn_ex_010.exp3.json","id":300251}],"nameLeft":"Natsuki","textLeft":"\"I CAN DO IT\"!@You can yell this one out yourself, got it?"},{"chara":[{"cheek":0,"face":"mtn_ex_011.exp3.json","id":801300}],"nameRight":"","textRight":"Yeah! I got it!@Thank you, Miss!"},{"autoTurnLast":0.5,"chara":[{"effect":"fadeout","id":801300}],"textClear":1},{"chara":[{"id":300251,"motion":300}],"nameLeft":"Natsuki","textLeft":"Phew~@I'm glad he found the courage."},{"chara":[{"cheek":0,"face":"mtn_ex_030.exp3.json","id":300801,"motion":1,"pos":2}],"nameRight":"Akira","textRight":"That's like a haunted house, so it's gotta be scary@for kids."},{"chara":[{"id":300251,"motion":100}],"nameLeft":"Natsuki","textLeft":"Yep."},{"chara":[{"cheek":0,"face":"mtn_ex_011.exp3.json","id":300251}],"nameLeft":"Natsuki","textLeft":"That's why I had them design my costume@to let me cheer people on."},{"chara":[{"cheek":0,"face":"mtn_ex_050.exp3.json","id":300801,"motion":200}],"nameRight":"Akira","textRight":"Oh, that's what you meant by being easy to move in."},{"chara":[{"cheek":0,"face":"mtn_ex_010.exp3.json","id":300251,"motion":0}],"nameLeft":"Natsuki","textLeft":"When I cried in a haunted house a long time ago,"},{"chara":[{"id":300251}],"nameLeft":"Natsuki","textLeft":"the ghost's staff cheered \"you'll be absolutely okay!\"@to keep me going,"},{"chara":[{"id":300251}],"nameLeft":"Natsuki","textLeft":"and because they encouraged me,"},{"chara":[{"id":300251},{"id":300801,"motion":0}],"nameLeft":"Natsuki","textLeft":"if I see the same thing happen,@I want to cheer them on."},{"chara":[{"cheek":1,"face":"mtn_ex_030.exp3.json","id":300251}],"nameLeft":"Natsuki","textLeft":"I was a little embarrassed actually trying this on,"},{"chara":[{"cheek":0,"face":"mtn_ex_011.exp3.json","id":300251,"motion":200}],"nameLeft":"Natsuki","textLeft":"but with this costume it's hard for people to get@scared. Well...I guess it turned out alright!"},{"nameCenter":"Kanagi's Voice","textBg":"shout","textCenter":"Utsuho! Apologies, but may I ask for your@assistance again?!"},{"chara":[{"cheek":0,"face":"mtn_ex_050.exp3.json","id":300251,"motion":400}],"nameLeft":"Natsuki","textLeft":"Ah— ...Right, work!@Okay, see you around, Akira!"},{"chara":[{"cheek":0,"face":"mtn_ex_011.exp3.json","id":300251,"motion":100}],"nameLeft":"Natsuki","textLeft":"Yes, yeees! I'll be right oveeer!"},{"autoTurnLast":0.5,"chara":[{"effect":"fadeout","id":300251}],"textClear":1},{"chara":[{"cheek":0,"face":"mtn_ex_030.exp3.json","id":300801}],"nameRight":"Akira","textRight":"Ah— ...There she goes...@Must be rough for her..."},{"chara":[{"cheek":0,"face":"mtn_ex_010.exp3.json","id":300801,"motion":100}],"nameRight":"Akira","textRight":"...Well...@If Natsuki's having fun then it's cool."},{"autoTurnLast":1.0,"bg":"bg_adv_21902.jpg","chara":[{"cheek":0,"face":"mtn_ex_011.exp3.json","id":801200,"motion":0,"pos":0},{"cheek":0,"face":"mtn_ex_011.exp3.json","id":300251,"motion":0,"pos":1},{"cheek":0,"face":"mtn_ex_011.exp3.json","id":801600,"motion":0,"pos":2}],"turnChangeIn":"fadeIn"},{"chara":[{"id":300251,"motion":100}],"nameNarration":"Natsuki","narration":"In the end, it was a very busy day, but I saw@way more smiling faces than crying ones,@so I think it turned out to be@a very fulfilling Halloween.","narrationBg":"","narrationCoverOpacity":110.0,"narrationEffect":"in","turnChangeOut":"fadeOut"},{"narration":"And so...@All is good and well!"},{"autoTurnLast":2.0,"turnChangeIn":"fadeIn"}]},"version":3}
